ReadWriteMemory/__init__.py
ReadWriteMemory-0.1.5.dist-info/LICENSE
ReadWriteMemory-0.1.5.dist-info/METADATA
ReadWriteMemory-0.1.5.dist-info/WHEEL
ReadWriteMemory-0.1.5.dist-info/top_level.txt
ReadWriteMemory-0.1.5.dist-info/RECORD
