Metadata-Version: 2.1
Name: ReadWriteMemory
Version: 0.1.5
Summary: ReadWriteMemory Class to work with Windows process memory and hacking video games.
Home-page: https://github.com/vsantiago113/ReadWriteMemory
Author: Victor M Santiago
Author-email: vsantiago113sec@gmail.com
License: MIT
Download-URL: https://github.com/vsantiago113/ReadWriteMemory/archive/0.1.5.zip
Keywords: ReadWriteMemory,Hacking,Cheat Engine
Platform: UNKNOWN
Classifier: Development Status :: 5 - Production/Stable
Classifier: Topic :: Utilities
Classifier: License :: OSI Approved :: MIT License
Classifier: Operating System :: MacOS :: MacOS X
Classifier: Operating System :: Microsoft :: Windows
Classifier: Operating System :: POSIX :: Linux
Classifier: Programming Language :: Python
Classifier: Intended Audience :: Developers
Classifier: Programming Language :: Python :: 3.4
Classifier: Programming Language :: Python :: 3.5
Classifier: Programming Language :: Python :: 3.6
Classifier: Programming Language :: Python :: 3.7
Classifier: Programming Language :: Python :: 3.8
Requires-Python: >=3.4.0
